tg_login/__init__.py
tg_login/cli.py
tg_login/login.py
tg_login-0.0.4.dist-info/entry_points.txt
tg_login-0.0.4.dist-info/LICENSE
tg_login-0.0.4.dist-info/WHEEL
tg_login-0.0.4.dist-info/METADATA
tg_login-0.0.4.dist-info/RECORD
