Metadata-Version: 2.1
Name: tg-login
Version: 0.0.4
Summary: A command line tool to login into Telegram with user or bot accounts.
Home-page: https://github.com/aahnik/tg-login
License: MIT
Author: aahnik
Author-email: daw@aahnik.dev
Requires-Python: >=3.10,<4.0
Classifier: License :: OSI Approved :: MIT License
Classifier: Programming Language :: Python :: 3
Classifier: Programming Language :: Python :: 3.10
Requires-Dist: Telethon (>=1.25.1,<2.0.0)
Requires-Dist: python-dotenv (>=0.21.0,<0.22.0)
Requires-Dist: typer (>=0.7.0,<0.8.0)
Project-URL: Repository, https://github.com/aahnik/tg-login
